{"id":"cmm81bcdx002xpa3wprd08g9o","slug":"neden-learnecohub","title":"Neden LearnecoHub?","createdAt":"2026-03-01T17:39:19.797Z","updatedAt":"2026-03-01T17:39:19.797Z","sections":[{"id":"cmm81bcmv002zpa3wfen8h8jo","pageId":"cmm81bcdx002xpa3wprd08g9o","sectionType":"subpage_hero","title":"Hero","order":1,"visible":true,"content":"{\"breadcrumb\":\"Neden LearnecoHub?\",\"tag\":\"NEDEN BİZ\",\"tagIcon\":\"Zap\",\"title\":\"Farkı\",\"titleHighlight\":\"hissedin.\",\"description\":\"LearnecoHub'i diğer platformlardan ayıran özellikler.\",\"theme\":\"mint\"}","createdAt":"2026-03-01T17:39:20.119Z","updatedAt":"2026-03-04T11:02:38.610Z"},{"id":"cmm81bcrd0031pa3wt79o6a9g","pageId":"cmm81bcdx002xpa3wprd08g9o","sectionType":"bento_grid","title":"Avantajlarımız","order":2,"visible":true,"content":"{\"items\":[{\"title\":\"Bilimsel Temelli Müfredat\",\"description\":\"CASEL çerçevesine dayalı, 20+ yıllık araştırma birikimiyle oluşturulmuş içerikler\",\"icon\":\"Brain\",\"color\":\"#1B3A7B\"},{\"title\":\"İnteraktif Öğrenme\",\"description\":\"Video dersler, oyunlar ve canlı seanslarla zenginleştirilmiş deneyim\",\"icon\":\"Gamepad2\",\"color\":\"#2ECC71\"},{\"title\":\"Bireysel İlerleme\",\"description\":\"Her çocuğun kendi hızında ilerleyebileceği kişiselleştirilmiş yollar\",\"icon\":\"TrendingUp\",\"color\":\"#7F63CB\"},{\"title\":\"Uzman Kadro\",\"description\":\"Psikiyatrist, psikolog ve pedagoglardan oluşan deneyimli ekip\",\"icon\":\"Users\",\"color\":\"#EE7A45\"},{\"title\":\"Aile Katılımı\",\"description\":\"Ebeveynlere özel rehberlik ve ev etkinlikleri\",\"icon\":\"Home\",\"color\":\"#F5C518\"},{\"title\":\"Ölçülebilir Sonuçlar\",\"description\":\"Detaylı ilerleme raporları ve gelişim takibi\",\"icon\":\"BarChart3\",\"color\":\"#1B3A7B\"}]}","createdAt":"2026-03-01T17:39:20.282Z","updatedAt":"2026-03-04T11:02:38.843Z"},{"id":"cmm81bcvv0033pa3wqk0kaztg","pageId":"cmm81bcdx002xpa3wprd08g9o","sectionType":"stats","title":"Rakamlarla Biz","order":3,"visible":true,"content":"{\"items\":[{\"icon\":\"Users\",\"value\":10000,\"suffix\":\"+\",\"label\":\"Aktif Öğrenci\",\"color\":\"#1B3A7B\",\"bgColor\":\"#EBF2FB\"},{\"icon\":\"Star\",\"value\":98,\"suffix\":\"%\",\"label\":\"Memnuniyet\",\"color\":\"#F5C518\",\"bgColor\":\"#FFFDE7\"},{\"icon\":\"Award\",\"value\":15,\"suffix\":\"+\",\"label\":\"Ödül\",\"color\":\"#EE7A45\",\"bgColor\":\"#FEF5F0\"},{\"icon\":\"Globe\",\"value\":8,\"suffix\":\"+\",\"label\":\"Şehir\",\"color\":\"#2ECC71\",\"bgColor\":\"#ECFBF2\"}]}","createdAt":"2026-03-01T17:39:20.444Z","updatedAt":"2026-03-04T11:02:39.074Z"},{"id":"cmm81bd4s0035pa3w69c0cirh","pageId":"cmm81bcdx002xpa3wprd08g9o","sectionType":"final_cta","title":"Son CTA","order":4,"visible":true,"content":"{\"title\":\"Siz de <span class=\\\"text-[#F5C518]\\\">farkı görmeye başlayabilirsiniz.</span>\",\"description\":\"Ücretsiz deneme ile LearnecoHub'in farkını yaşayın.\",\"cta\":{\"label\":\"Ücretsiz Başla\",\"href\":\"https://lms.learnecohub.com/login/index.php\"},\"phone\":{\"label\":\"0531 952 94 96\",\"href\":\"tel:+905319529496\"},\"badges\":[{\"text\":\"14 gün ücretsiz\"},{\"text\":\"Kredi kartı gerekmiyor\"},{\"text\":\"Anında erişim\"}]}","createdAt":"2026-03-01T17:39:20.605Z","updatedAt":"2026-03-04T11:53:11.572Z"}]}